pyvcc-1.3.1.dist-info/METADATA
pyvcc-1.3.1.dist-info/WHEEL
pyvcc-1.3.1.dist-info/entry_points.txt
pyvcc-1.3.1.dist-info/licenses/LICENSE
pyvcc/__init__.py
pyvcc/__main__.py
pyvcc/cli.py
pyvcc/semver.py
pyvcc-1.3.1.dist-info/RECORD
