Metadata-Version: 2.1
Name: PyVCC
Version: 1.3.1
Summary: PyVCC python version controller using conventional commits
Requires-Python: >=3.10
Requires-Dist: pygit2>=1.18.0
Requires-Dist: structlog>=25.3.0
Requires-Dist: typing-extensions>=4.0.0; python_version < "3.11"
